autocov
